HulianwangGongsiChangyongKuangjiaYuanmaShangxi/README.md
HulianwangGongsiChangyongKuangjiaYuanmaShangxi/__init__.py
HulianwangGongsiChangyongKuangjiaYuanmaShangxi/__main__.py
HulianwangGongsiChangyongKuangjiaYuanmaShangxi/file.epub
HulianwangGongsiChangyongKuangjiaYuanmaShangxi/index.html
HulianwangGongsiChangyongKuangjiaYuanmaShangxi/css/__init__.py
HulianwangGongsiChangyongKuangjiaYuanmaShangxi/css/annotations.css
HulianwangGongsiChangyongKuangjiaYuanmaShangxi/css/main.css
HulianwangGongsiChangyongKuangjiaYuanmaShangxi/css/normalize.css
HulianwangGongsiChangyongKuangjiaYuanmaShangxi/css/popup.css
HulianwangGongsiChangyongKuangjiaYuanmaShangxi/font/__init__.py
HulianwangGongsiChangyongKuangjiaYuanmaShangxi/font/fontello.eot
HulianwangGongsiChangyongKuangjiaYuanmaShangxi/font/fontello.svg
HulianwangGongsiChangyongKuangjiaYuanmaShangxi/font/fontello.ttf
HulianwangGongsiChangyongKuangjiaYuanmaShangxi/font/fontello.woff
HulianwangGongsiChangyongKuangjiaYuanmaShangxi/img/__init__.py
HulianwangGongsiChangyongKuangjiaYuanmaShangxi/img/annotator-glyph-sprite.png
HulianwangGongsiChangyongKuangjiaYuanmaShangxi/img/annotator-icon-sprite.png
HulianwangGongsiChangyongKuangjiaYuanmaShangxi/img/apple-touch-icon.png
HulianwangGongsiChangyongKuangjiaYuanmaShangxi/img/cancelfullscreen.png
HulianwangGongsiChangyongKuangjiaYuanmaShangxi/img/close.png
HulianwangGongsiChangyongKuangjiaYuanmaShangxi/img/fullscreen.png
HulianwangGongsiChangyongKuangjiaYuanmaShangxi/img/loader.gif
HulianwangGongsiChangyongKuangjiaYuanmaShangxi/img/menu-icon.png
HulianwangGongsiChangyongKuangjiaYuanmaShangxi/img/save.png
HulianwangGongsiChangyongKuangjiaYuanmaShangxi/img/saved.png
HulianwangGongsiChangyongKuangjiaYuanmaShangxi/img/settings-s.png
HulianwangGongsiChangyongKuangjiaYuanmaShangxi/img/settings.png
HulianwangGongsiChangyongKuangjiaYuanmaShangxi/img/star.png
HulianwangGongsiChangyongKuangjiaYuanmaShangxi/js/__init__.py
HulianwangGongsiChangyongKuangjiaYuanmaShangxi/js/epub.js
hulianwang_gongsi_changyong_kuangjia_yuanma_shangxi-2024.3.6.0.dist-info/METADATA
hulianwang_gongsi_changyong_kuangjia_yuanma_shangxi-2024.3.6.0.dist-info/WHEEL
hulianwang_gongsi_changyong_kuangjia_yuanma_shangxi-2024.3.6.0.dist-info/entry_points.txt
hulianwang_gongsi_changyong_kuangjia_yuanma_shangxi-2024.3.6.0.dist-info/top_level.txt
hulianwang_gongsi_changyong_kuangjia_yuanma_shangxi-2024.3.6.0.dist-info/RECORD
